Workbook

Sheet DCF & Valuation
A1: CMP & Company Input
A2: Input Parameter | B2: Value | C2: Notes / Source
A3: Company Name | B3: Transrail Lighting
A4: NSE/BSE Ticker | B4: TRANSRAILL
A5: Face Value | B5: 2
A6: Equity Capital | B6: 26.85
A7: Shares Outstanding (Cr.) | B7: =B6/B5 -> 13.425 | C7: Equity capital/FV
A8: CMP (₹) | B8: 481.7 | C8: Live or last traded price
A9: Market Cap (₹ Cr.) | B9: =B8*B7 -> 6466.8225
A10: Total Debt (₹ Cr.) | B10: 678 | C10: Long term + Short term
A11: Cash & Equivalents (₹ Cr.) | B11: 763 | C11: Latest balance sheet
A12: Net Debt (₹ Cr.) | B12: =B10-B11 -> -85 | C12: Total debt - Cash
A13: Enterprise Value @ CMP (₹ Cr.) | B13: =B9+B12 -> 6381.8225 | C13: EV = Market Cap + Net Debt
A16: Assumptions (Revenue growth & EBITDA Margins)
A17: Assumption | B17: Base Input (FY26) | C17: FY27E | D17: FY28E | E17: FY29E
A18: Revenue Assumptions (₹ Cr.)
A19: FY26 Revenue (₹ Cr.) | B19: 6880
A20: Bear Case - Revenue Growth % | C20: 0.18 | D20: 0.16 | E20: 0.14
A21: Base Case - Revenue Growth % | C21: 0.2 | D21: 0.18 | E21: 0.16
A22: Bull Case - Revenue Growth % | C22: 0.22 | D22: 0.2 | E22: 0.18
A23: EBITDA Margins Assumptions
A24: Bear Case — EBITDA Margin % | C24: 0.105 | D24: 0.105 | E24: 0.105
A25: Base Case — EBITDA Margin % | C25: 0.115 | D25: 0.116 | E25: 0.117
A26: Bull Case — EBITDA Margin % | C26: 0.125 | D26: 0.125 | E26: 0.125
A27: FCFF / Bridge Assumptions
A28: Tax Rate % | B28: =Assumptions!B17 -> 0.2517
A29: D&A (₹ Cr.) - FY27E | B29: 78.6
A30: D&A (₹ Cr.) - FY28E | B30: 107.1
A31: D&A (₹ Cr.) - FY29E | B31: 120.9
A32: Capex (₹ Cr.) - FY27E | B32: 185
A33: Capex (₹ Cr.) - FY28E | B33: 209
A34: Capex (₹ Cr.) - FY29E | B34: 192.8
A35: Δ NWC (₹ Cr.) - FY27E | B35: 186.5
A36: Δ NWC (₹ Cr.) - FY28E | B36: 337.2
A37: Δ NWC (₹ Cr.) - FY29E | B37: 471.3
A38: WACC Assumptions
A39: Risk-free Rate (IN10Y yield-Bond default spread) | B39: =Assumptions!B4 -> 0.0565 | C39: Changes made in "Assumptions" sheet will get reflected here
A40: Equity Risk Premium % | B40: =Assumptions!B13 -> 0.12266803
A41: Beta (Levered) | B41: =Assumptions!B18 -> 0.86800959
A42: Cost of Debt (pre-tax %) | B42: =Assumptions!B22 -> 0.10516553
A43: Tax Rate for WACC % | B43: =Assumptions!B23 -> 0.2517
A44: Total Equity (₹ Cr.) | B44: =Assumptions!B27 -> 2281
A45: Total Debt (₹ Cr.) | B45: =Assumptions!B26 -> 678
A46: WACC | B46: =Assumptions!B29 -> 0.14366544
A47: Terminal Growth Rate % | B47: =Assumptions!B31 -> 0.045
A48: EV/EBITDA Exit Multiple (x) | B48: =Assumptions!B33 -> 9
A50: DCF & Valuation Model (₹ Cr.)
B51: FY26A | C51: FY27E | D51: FY28E | E51: FY29E
A52: Revenue Scenarios (₹ Cr.)
A53: Bear Case — Revenue Growth % | C53: ='DCF & Valuation'!C20 -> 0.18 | D53: ='DCF & Valuation'!D20 -> 0.16 | E53: ='DCF & Valuation'!E20 -> 0.14
A54: Base Case — Revenue Growth % | C54: ='DCF & Valuation'!C21 -> 0.2 | D54: ='DCF & Valuation'!D21 -> 0.18 | E54: ='DCF & Valuation'!E21 -> 0.16
A55: Bull Case — Revenue Growth % | C55: ='DCF & Valuation'!C22 -> 0.22 | D55: ='DCF & Valuation'!D22 -> 0.2 | E55: ='DCF & Valuation'!E22 -> 0.18
A56: Bear Case — Revenue (₹ Cr.) | B56: ='DCF & Valuation'!B19 -> 6880 | C56: =B56*(1+C53) -> 8118.4 | D56: =C56*(1+D53) -> 9417.344 | E56: =D56*(1+E53) -> 10735.772
A57: Base Case — Revenue (₹ Cr.) | B57: ='DCF & Valuation'!B19 -> 6880 | C57: =B57*(1+C54) -> 8256 | D57: =C57*(1+D54) -> 9742.08 | E57: =D57*(1+E54) -> 11300.813
A58: Bull Case — Revenue (₹ Cr.) | B58: ='DCF & Valuation'!B19 -> 6880 | C58: =B58*(1+C55) -> 8393.6 | D58: =C58*(1+D55) -> 10072.32 | E58: =D58*(1+E55) -> 11885.338
A60: EBITDA Bridge - Margin × Revenue (₹ Cr.) | C60: FY27E | D60: FY28E | E60: FY29E
A61: Bear Case — EBITDA Margin % | C61: ='DCF & Valuation'!C24 -> 0.105 | D61: ='DCF & Valuation'!D24 -> 0.105 | E61: ='DCF & Valuation'!E24 -> 0.105
A62: Base Case — EBITDA Margin % | C62: ='DCF & Valuation'!C25 -> 0.115 | D62: ='DCF & Valuation'!D25 -> 0.116 | E62: ='DCF & Valuation'!E25 -> 0.117
A63: Bull Case — EBITDA Margin % | C63: ='DCF & Valuation'!C26 -> 0.125 | D63: ='DCF & Valuation'!D26 -> 0.125 | E63: ='DCF & Valuation'!E26 -> 0.125
A64: Bear Case — EBITDA (₹ Cr.) | C64: =C56*C61 -> 852.432 | D64: =D56*D61 -> 988.82112 | E64: =E56*E61 -> 1127.2561
A65: Base Case — EBITDA (₹ Cr.) | C65: =C57*C62 -> 949.44 | D65: =D57*D62 -> 1130.0813 | E65: =E57*E62 -> 1322.1951
A66: Bull Case — EBITDA (₹ Cr.) | C66: =C58*C63 -> 1049.2 | D66: =D58*D63 -> 1259.04 | E66: =E58*E63 -> 1485.6672
A68: FCFF Waterfall - Base Case (₹ Cr.) | C68: FY27E | D68: FY28E | E68: FY29E | G68: FCFF Waterfall - Bear Case (₹ Cr.) | I68: FY27E | J68: FY28E | K68: FY29E | M68: FCFF Waterfall - Bull Case (₹ Cr.) | O68: FY27E | P68: FY28E | Q68: FY29E
A69: EBITDA | C69: =C65 -> 949.44 | D69: =D65 -> 1130.0813 | E69: =E65 -> 1322.1951 | G69: EBITDA | I69: =C64 -> 852.432 | J69: =D64 -> 988.82112 | K69: =E64 -> 1127.2561 | M69: EBITDA | O69: =C66 -> 1049.2 | P69: =D66 -> 1259.04 | Q69: =E66 -> 1485.6672
A70: (-) Depreciation & Amort. | C70: ='DCF & Valuation'!B29 -> 78.6 | D70: ='DCF & Valuation'!B30 -> 107.1 | E70: ='DCF & Valuation'!B31 -> 120.9 | G70: (-) Depreciation & Amort. | I70: =B29 -> 78.6 | J70: =B30 -> 107.1 | K70: =B31 -> 120.9 | M70: (-) Depreciation & Amort. | O70: =B29 -> 78.6 | P70: =B30 -> 107.1 | Q70: =B31 -> 120.9
A71: EBIT | C71: =C69-C70 -> 870.84 | D71: =D69-D70 -> 1022.9813 | E71: =E69-E70 -> 1201.2951 | G71: EBIT | I71: =I69-I70 -> 773.832 | J71: =J69-J70 -> 881.72112 | K71: =K69-K70 -> 1006.3561 | M71: EBIT | O71: =O69-O70 -> 970.6 | P71: =P69-P70 -> 1151.94 | Q71: =Q69-Q70 -> 1364.7672
A72: (-) Tax on EBIT | C72: =C71*$B$28 -> 219.19043 | D72: =D71*$B$28 -> 257.48439 | E72: =E71*$B$28 -> 302.36598 | G72: (-) Tax on EBIT | I72: =I71*$B$28 -> 194.77351 | J72: =J71*$B$28 -> 221.92921 | K72: =K71*$B$28 -> 253.29982 | M72: (-) Tax on EBIT | O72: =O71*$B$28 -> 244.30002 | P72: =P71*$B$28 -> 289.9433 | Q72: =Q71*$B$28 -> 343.5119
A73: NOPAT | C73: =C71-C72 -> 651.64957 | D73: =D71-D72 -> 765.49689 | E73: =E71-E72 -> 898.92912 | G73: NOPAT | I73: =I71-I72 -> 579.05849 | J73: =J71-J72 -> 659.79191 | K73: =K71-K72 -> 753.05625 | M73: NOPAT | O73: =O71-O72 -> 726.29998 | P73: =P71-P72 -> 861.9967 | Q73: =Q71-Q72 -> 1021.2553
A74: (+) D&A add-back | C74: =C70 -> 78.6 | D74: =D70 -> 107.1 | E74: =E70 -> 120.9 | G74: (+) D&A add-back | I74: =I70 -> 78.6 | J74: =J70 -> 107.1 | K74: =K70 -> 120.9 | M74: (+) D&A add-back | O74: =O70 -> 78.6 | P74: =P70 -> 107.1 | Q74: =Q70 -> 120.9
A75: (-) Maintenance Capex | C75: =('DCF & Valuation'!B32) -> 185 | D75: =('DCF & Valuation'!B33) -> 209 | E75: =('DCF & Valuation'!B34) -> 192.8 | G75: (-) Maintenance Capex | I75: =B32 -> 185 | J75: =B33 -> 209 | K75: =B34 -> 192.8 | M75: (-) Maintenance Capex | O75: =B32 -> 185 | P75: =B33 -> 209 | Q75: =B34 -> 192.8
A76: (-) Δ Net Working Capital | C76: =('DCF & Valuation'!B35) -> 186.5 | D76: =('DCF & Valuation'!B36) -> 337.2 | E76: =('DCF & Valuation'!B37) -> 471.3 | G76: (-) Δ Net Working Capital | I76: =B35 -> 186.5 | J76: =B36 -> 337.2 | K76: =B37 -> 471.3 | M76: (-) Δ Net Working Capital | O76: =B35 -> 186.5 | P76: =B36 -> 337.2 | Q76: =B37 -> 471.3
A77: FCFF | C77: =C73+C74-C75-C76 -> 358.74957 | D77: =D73+D74-D75-D76 -> 326.39689 | E77: =E73+E74-E75-E76 -> 355.72912 | G77: FCFF | I77: =I73+I74-I75-I76 -> 286.15849 | J77: =J73+J74-J75-J76 -> 220.69191 | K77: =K73+K74-K75-K76 -> 209.85625 | M77: FCFF | O77: =O73+O74-O75-O76 -> 433.39998 | P77: =P73+P74-P75-P76 -> 422.8967 | Q77: =Q73+Q74-Q75-Q76 -> 478.0553
A78: PV of FCFF | C78: =C77/(1+$B$46)^1 -> 313.68402 | D78: =D77/(1+$B$46)^2 -> 249.54451 | E78: =E77/(1+$B$46)^3 -> 237.80579 | G78: PV of FCFF | I78: =I77/(1+$B$46)^1 -> 250.21171 | J78: =J77/(1+$B$46)^2 -> 168.72849 | K78: =K77/(1+$B$46)^3 -> 140.28942 | M78: PV of FCFF | O78: =O77/(1+$B$46)^1 -> 378.95696 | P78: =P77/(1+$B$46)^2 -> 323.32278 | Q78: =Q77/(1+$B$46)^3 -> 319.58114
A80: VALUATION TABLE — Bear / Base / Bull (₹ Cr. and ₹ per share) - EV/EBITDA Exit Multiple
A81: Metric | B81: Bear Case (₹ Cr.) | C81: Base Case (₹ Cr.) | D81: Bull Case (₹ Cr.)
A82: FY29E EBITDA (₹ Cr.) | B82: =E64 -> 1127.2561 | C82: =E65 -> 1322.1951 | D82: =E66 -> 1485.6672
A83: Terminal Value @Multiple× EV/EBITDA (₹ Cr.) | B83: =B82*$B$48 -> 10145.305 | C83: =C82*$B$48 -> 11899.756 | D83: =D82*$B$48 -> 13371.005
A84: PV of Terminal Value (₹ Cr.) | B84: =B83/(1+$B$46)^3 -> 6782.1611 | C84: =C83/(1+$B$46)^3 -> 7955.016 | D84: =D83/(1+$B$46)^3 -> 8938.5495
A85: PV of FCFFs FY27-29 (₹ Cr.) | B85: =SUM(I78:K78) -> 559.22962 | C85: =SUM($C$78:$E$78) -> 801.03432 | D85: =SUM(O78:Q78) -> 1021.8609
A86: Enterprise Value (₹ Cr.) | B86: =B84+B85 -> 7341.3907 | C86: =C84+C85 -> 8756.0503 | D86: =D84+D85 -> 9960.4104
A87: (-) Net Debt (₹ Cr.) | B87: ='DCF & Valuation'!$B$12 -> -85 | C87: ='DCF & Valuation'!$B$12 -> -85 | D87: ='DCF & Valuation'!$B$12 -> -85
A88: Equity Value (₹ Cr.) | B88: =B86-B87 -> 7426.3907 | C88: =C86-C87 -> 8841.0503 | D88: =D86-D87 -> 10045.41
A89: Equity Value / Share (₹) | B89: =B88/'DCF & Valuation'!$B$7 -> 553.17621 | C89: =C88/'DCF & Valuation'!$B$7 -> 658.55123 | D89: =D88/'DCF & Valuation'!$B$7 -> 748.26148
A90: CMP (₹) - live from CMP Input | B90: ='DCF & Valuation'!$B$8 -> 481.7 | C90: ='DCF & Valuation'!$B$8 -> 481.7 | D90: ='DCF & Valuation'!$B$8 -> 481.7
A91: Upside / (Downside) % | B91: =B89/B90-1 -> 0.14838326 | C91: =C89/C90-1 -> 0.36713978 | D91: =D89/D90-1 -> 0.55337654
A93: Implied Equity Value/Share (₹) Using GGM | WACC (rows) × Terminal Growth Rate (columns)
A94: WACC ↓ / TGR → | B94: 0.02 | C94: 0.03 | D94: 0.04 | E94: 0.05 | F94: 0.06
A95: 0.12 | B95: =((E77*(1+0.02)/(0.12-0.02)/(1+0.12)^3)+(C77/(1+0.12)^1+D77/(1+0.12)^2+E77/(1+0.12)^3)-'DCF & Valuation'!B12)/'DCF & Valuation'!B7 -> 260.80927 | C95: =((E77*(1+0.03)/(0.12-0.03)/(1+0.12)^3)+(C77/(1+0.12)^1+D77/(1+0.12)^2+E77/(1+0.12)^3)-'DCF & Valuation'!B12)/'DCF & Valuation'!B7 -> 284.28 | D95: =((E77*(1+0.04)/(0.12-0.04)/(1+0.12)^3)+(C77/(1+0.12)^1+D77/(1+0.12)^2+E77/(1+0.12)^3)-'DCF & Valuation'!B12)/'DCF & Valuation'!B7 -> 313.61841 | E95: =((E77*(1+0.05)/(0.12-0.05)/(1+0.12)^3)+(C77/(1+0.12)^1+D77/(1+0.12)^2+E77/(1+0.12)^3)-'DCF & Valuation'!B12)/'DCF & Valuation'!B7 -> 351.33923 | F95: =((E77*(1+0.06)/(0.12-0.06)/(1+0.12)^3)+(C77/(1+0.12)^1+D77/(1+0.12)^2+E77/(1+0.12)^3)-'DCF & Valuation'!B12)/'DCF & Valuation'!B7 -> 401.63365
A96: 0.13 | B96: =((E77*(1+0.02)/(0.13-0.02)/(1+0.13)^3)+(C77/(1+0.13)^1+D77/(1+0.13)^2+E77/(1+0.13)^3)-'DCF & Valuation'!B12)/'DCF & Valuation'!B7 -> 237.6695 | C96: =((E77*(1+0.03)/(0.13-0.03)/(1+0.13)^3)+(C77/(1+0.13)^1+D77/(1+0.13)^2+E77/(1+0.13)^3)-'DCF & Valuation'!B12)/'DCF & Valuation'!B7 -> 256.53445 | D96: =((E77*(1+0.04)/(0.13-0.04)/(1+0.13)^3)+(C77/(1+0.13)^1+D77/(1+0.13)^2+E77/(1+0.13)^3)-'DCF & Valuation'!B12)/'DCF & Valuation'!B7 -> 279.5916 | E96: =((E77*(1+0.05)/(0.13-0.05)/(1+0.13)^3)+(C77/(1+0.13)^1+D77/(1+0.13)^2+E77/(1+0.13)^3)-'DCF & Valuation'!B12)/'DCF & Valuation'!B7 -> 308.41305 | F96: =((E77*(1+0.06)/(0.13-0.06)/(1+0.13)^3)+(C77/(1+0.13)^1+D77/(1+0.13)^2+E77/(1+0.13)^3)-'DCF & Valuation'!B12)/'DCF & Valuation'!B7 -> 345.46919
A97: 0.14 | B97: =((E77*(1+0.02)/(0.14-0.02)/(1+0.14)^3)+(C77/(1+0.14)^1+D77/(1+0.14)^2+E77/(1+0.14)^3)-'DCF & Valuation'!B12)/'DCF & Valuation'!B7 -> 218.38817 | C97: =((E77*(1+0.03)/(0.14-0.03)/(1+0.14)^3)+(C77/(1+0.14)^1+D77/(1+0.14)^2+E77/(1+0.14)^3)-'DCF & Valuation'!B12)/'DCF & Valuation'!B7 -> 233.83436 | D97: =((E77*(1+0.04)/(0.14-0.04)/(1+0.14)^3)+(C77/(1+0.14)^1+D77/(1+0.14)^2+E77/(1+0.14)^3)-'DCF & Valuation'!B12)/'DCF & Valuation'!B7 -> 252.36979 | E97: =((E77*(1+0.05)/(0.14-0.05)/(1+0.14)^3)+(C77/(1+0.14)^1+D77/(1+0.14)^2+E77/(1+0.14)^3)-'DCF & Valuation'!B12)/'DCF & Valuation'!B7 -> 275.02421 | F97: =((E77*(1+0.06)/(0.14-0.06)/(1+0.14)^3)+(C77/(1+0.14)^1+D77/(1+0.14)^2+E77/(1+0.14)^3)-'DCF & Valuation'!B12)/'DCF & Valuation'!B7 -> 303.34224
A98: 0.15 | B98: =((E77*(1+0.02)/(0.15-0.02)/(1+0.15)^3)+(C77/(1+0.15)^1+D77/(1+0.15)^2+E77/(1+0.15)^3)-'DCF & Valuation'!B12)/'DCF & Valuation'!B7 -> 202.07478 | C98: =((E77*(1+0.03)/(0.15-0.03)/(1+0.15)^3)+(C77/(1+0.15)^1+D77/(1+0.15)^2+E77/(1+0.15)^3)-'DCF & Valuation'!B12)/'DCF & Valuation'!B7 -> 214.91832 | D98: =((E77*(1+0.04)/(0.15-0.04)/(1+0.15)^3)+(C77/(1+0.15)^1+D77/(1+0.15)^2+E77/(1+0.15)^3)-'DCF & Valuation'!B12)/'DCF & Valuation'!B7 -> 230.09705 | E98: =((E77*(1+0.05)/(0.15-0.05)/(1+0.15)^3)+(C77/(1+0.15)^1+D77/(1+0.15)^2+E77/(1+0.15)^3)-'DCF & Valuation'!B12)/'DCF & Valuation'!B7 -> 248.31153 | F98: =((E77*(1+0.06)/(0.15-0.06)/(1+0.15)^3)+(C77/(1+0.15)^1+D77/(1+0.15)^2+E77/(1+0.15)^3)-'DCF & Valuation'!B12)/'DCF & Valuation'!B7 -> 270.57367
A99: 0.16 | B99: =((E77*(1+0.02)/(0.16-0.02)/(1+0.16)^3)+(C77/(1+0.16)^1+D77/(1+0.16)^2+E77/(1+0.16)^3)-'DCF & Valuation'!B12)/'DCF & Valuation'!B7 -> 188.09327 | C99: =((E77*(1+0.03)/(0.16-0.03)/(1+0.16)^3)+(C77/(1+0.16)^1+D77/(1+0.16)^2+E77/(1+0.16)^3)-'DCF & Valuation'!B12)/'DCF & Valuation'!B7 -> 198.91303 | D99: =((E77*(1+0.04)/(0.16-0.04)/(1+0.16)^3)+(C77/(1+0.16)^1+D77/(1+0.16)^2+E77/(1+0.16)^3)-'DCF & Valuation'!B12)/'DCF & Valuation'!B7 -> 211.53609 | E99: =((E77*(1+0.05)/(0.16-0.05)/(1+0.16)^3)+(C77/(1+0.16)^1+D77/(1+0.16)^2+E77/(1+0.16)^3)-'DCF & Valuation'!B12)/'DCF & Valuation'!B7 -> 226.45425 | F99: =((E77*(1+0.06)/(0.16-0.06)/(1+0.16)^3)+(C77/(1+0.16)^1+D77/(1+0.16)^2+E77/(1+0.16)^3)-'DCF & Valuation'!B12)/'DCF & Valuation'!B7 -> 244.35604
A100: 0.17 | B100: =((E77*(1+0.02)/(0.17-0.02)/(1+0.17)^3)+(C77/(1+0.17)^1+D77/(1+0.17)^2+E77/(1+0.17)^3)-'DCF & Valuation'!B12)/'DCF & Valuation'!B7 -> 175.9772 | C100: =((E77*(1+0.03)/(0.17-0.03)/(1+0.17)^3)+(C77/(1+0.17)^1+D77/(1+0.17)^2+E77/(1+0.17)^3)-'DCF & Valuation'!B12)/'DCF & Valuation'!B7 -> 185.19472 | D100: =((E77*(1+0.04)/(0.17-0.04)/(1+0.17)^3)+(C77/(1+0.17)^1+D77/(1+0.17)^2+E77/(1+0.17)^3)-'DCF & Valuation'!B12)/'DCF & Valuation'!B7 -> 195.83032 | E100: =((E77*(1+0.05)/(0.17-0.05)/(1+0.17)^3)+(C77/(1+0.17)^1+D77/(1+0.17)^2+E77/(1+0.17)^3)-'DCF & Valuation'!B12)/'DCF & Valuation'!B7 -> 208.23852 | F100: =((E77*(1+0.06)/(0.17-0.06)/(1+0.17)^3)+(C77/(1+0.17)^1+D77/(1+0.17)^2+E77/(1+0.17)^3)-'DCF & Valuation'!B12)/'DCF & Valuation'!B7 -> 222.90276

Sheet Assumptions
A1: Particulars
A2: 10y Gov Bond | B2: 0.074
A3: Bond default spread | B3: 0.0175
A4: Rf | B4: =B2-B3 -> 0.0565
A6: Mature market ERP | B6: 0.0442 | D6: Revenue sources (%) | G6: Middle East Countries | H6: ERP | J6: North Africa Countries
A7: India country risk premium | B7: =B8*(B9/B10) -> 0.094694269 | D7: Domestic | E7: 0.45 | G7: Abu Dhabi | H7: 0.0481 | J7: Egypt | K7: 0.1348
A8: Default spread | B8: =B3 -> 0.0175 | D8: International | E8: =1-E7 -> 0.55 | G8: Bahrain | H8: 0.1101 | J8: Morocco | K8: 0.073
A9: SD Equity | B9: 0.16233303 | G9: Iraq | H9: 0.1348 | J9: Tunisia | K9: 0.1348
A10: SD Bond | B10: 0.03 | D10: Revenue weighted ERP | G10: Israel | H10: 0.0618 | J10: Algeria | K10: 0.0977
A11: India ERP | B11: =B6+B7 -> 0.13889427 | D11: India ERP | E11: =B11*E7 -> 0.062502421 | G11: Jordan | H11: 0.0865 | J11: Iran | K11: 0.1534
A12: MENA EPR | B12: =K15 -> 0.10939201 | D12: MENA EPR | E12: =B12*E8 -> 0.060165605 | G12: Kuwait | H12: 0.0507 | J12: Libya | K12: 0.0977
A13: Total ERP | B13: =SUM(E11:E12) -> 0.12266803 | G13: Lebanon | H13: 0.314 | J13: Yemen | K13: 0.1905 | L13: =AVERAGE(K7:K13) -> 0.12598571
G14: Oman | H14: 0.069181326
A15: Unlevered beta (Sector) | B15: ='Beta calculation'!U4 -> 0.70887438 | G15: Qatar | H15: 0.0481 | J15: MENA Region ERP | K15: =AVERAGE(L13,I17) -> 0.10939201
A16: Target D/E | B16: 0.3 | G16: Saudi Arabia | H16: 0.0494
A17: Tax rate | B17: 0.2517 | G17: United Arab Emirates | H17: 0.0481 | I17: =AVERAGE(H7:H17) -> 0.092798302
A18: Re-levered beta | B18: =B15*(1+(1-B17)*B16) -> 0.86800959
A20: Cost of equity | B20: =B4+(B18*B13) -> 0.16297702
A22: Pretax cost of debt | B22: =G25 -> 0.10516553 | D22: Facility | E22: FY25 Amount | F22: Rate | G22: Weighted cost
A23: Tax rate | B23: 0.2517 | D23: LT Term Loans | E23: 136.86 | F23: 0.085 | G23: =F23*(E23/$E$25) -> 0.016437201
A24: Post tax cost of debt | B24: =B22*(1-B23) -> 0.078695366 | D24: ST CC/WCDL | E24: 570.87 | F24: 0.11 | G24: =F24*(E24/$E$25) -> 0.088728329
E25: =SUM(E23:E24) -> 707.73 | G25: =SUM(G23:G24) -> 0.10516553
A26: Total Debt (FY26E) | B26: 678 | C26: =B26/SUM($B$26:$B$27) -> 0.22913146
A27: Total Equity (FY26E) | B27: 2281 | C27: =B27/SUM($B$26:$B$27) -> 0.77086854
A29: WACC | B29: =(B24*C26)+(B20*C27) -> 0.14366544
A31: Terminal growth rate % | B31: 0.045
A33: EV/EBITDA Exit multiple | B33: 9

Sheet Beta calculation
A1: Date | B1: CNX500 | C1: % return | D1: KEC International | E1: % return | H1: Kalpataru Projects | I1: % return | L1: Skipper | M1: % return | P1: Bajaj electricals | Q1: % return
A2: 44197 | B2: 11574.85 | D2: 354.59453 | H2: 293.67428 | L2: 65.470728 | P2: 536.25852
A3: 44200 | B3: 11691.8 | C3: =B3/B2-1 -> 0.01010382 | D3: 359.12289 | E3: =D3/D2-1 -> 0.012770533 | F3: Levered beta | G3: =SLOPE(E3:E1435,$C$3:$C$1435) -> 1.0334993 | H3: 296.21312 | I3: =H3/H2-1 -> 0.0086450799 | J3: Levered beta | K3: =SLOPE(I3:I1435,$C$3:$C$1435) -> 0.92791843 | L3: 66.248978 | M3: =L3/L2-1 -> 0.011886993 | N3: Levered beta | O3: =SLOPE(M3:M1435,$C$3:$C$1435) -> 1.5910694 | P3: 537.88278 | Q3: =P3/P2-1 -> 0.0030288627 | R3: Levered beta | S3: =SLOPE(Q3:Q1435,$C$3:$C$1435) -> 0.85009433 | U3: Total weighted avg unlevered beta
A4: 44201 | B4: 11767 | C4: =B4/B3-1 -> 0.006431875 | D4: 361.45856 | E4: =D4/D3-1 -> 0.006503796 | F4: debt to equity | G4: 0.87 | H4: 293.16649 | I4: =H4/H3-1 -> -0.010285242 | J4: debt to equity | K4: 0.46 | L4: 65.227523 | M4: =L4/L3-1 -> -0.015418428 | N4: debt to equity | O4: 0.63 | P4: 545.6966 | Q4: =P4/P3-1 -> 0.014527005 | R4: debt to equity | S4: 0.1 | U4: =(G6*G8)+(K6*K8)+(O6*O8)+(S6*S8) -> 0.70887438
A5: 44202 | B5: 11737.9 | C5: =B5/B4-1 -> -0.0024729846 | D5: 353.35517 | E5: =D5/D4-1 -> -0.022418568 | F5: Tax rate | G5: 0.2517 | H5: 301.93702 | I5: =H5/H4-1 -> 0.02991655 | J5: Tax rate | K5: 0.2517 | L5: 63.379165 | M5: =L5/L4-1 -> -0.028337074 | N5: Tax rate | O5: 0.2517 | P5: 552.72029 | Q5: =P5/P4-1 -> 0.012871048 | R5: Tax rate | S5: 0.2517
A6: 44203 | B6: 11766.1 | C6: =B6/B5-1 -> 0.0024024074 | D6: 349.25583 | E6: =D6/D5-1 -> -0.011601187 | F6: unlevered beta | G6: =G3/(1+(1-G5)*G4) -> 0.62597588 | H6: 310.06132 | I6: =H6/H5-1 -> 0.026907263 | J6: unlevered beta | K6: =K3/(1+(1-K5)*K4) -> 0.69030353 | L6: 65.811213 | M6: =L6/L5-1 -> 0.038372976 | N6: unlevered beta | O6: =O3/(1+(1-O5)*O4) -> 1.081309 | P6: 559.52449 | Q6: =P6/P5-1 -> 0.012310382 | R6: unlevered beta | S6: =S3/(1+(1-S5)*S4) -> 0.7909105
A7: 44204 | B7: 11925.6 | C7: =B7/B6-1 -> 0.013555894 | D7: 345.44248 | E7: =D7/D6-1 -> -0.01091852 | F7: Revenue (₹ Cr.) | G7: 23506 | H7: 324.32495 | I7: =H7/H6-1 -> 0.046002619 | J7: Revenue (₹ Cr.) | K7: 27380 | L7: 68.82695 | M7: =L7/L6-1 -> 0.045824065 | N7: Revenue (₹ Cr.) | O7: 5609 | P7: 584.15128 | Q7: =P7/P6-1 -> 0.044013793 | R7: Revenue (₹ Cr.) | S7: 4487
A8: 44207 | B8: 12006.5 | C8: =B8/B7-1 -> 0.0067837587 | D8: 347.77814 | E8: =D8/D7-1 -> 0.0067613631 | F8: % Revenue of Total | G8: =G7/(SUM($G$7,$K$7,$O$7,$S$7)) -> 0.385458 | H8: 314.67739 | I8: =H8/H7-1 -> -0.029746599 | J8: % Revenue of Total | K8: =K7/(SUM($G$7,$K$7,$O$7,$S$7)) -> 0.44898495 | L8: 67.027237 | M8: =L8/L7-1 -> -0.026148379 | N8: % Revenue of Total | O8: =O7/(SUM($G$7,$K$7,$O$7,$S$7)) -> 0.091977961 | P8: 618.65518 | Q8: =P8/P7-1 -> 0.059066718 | R8: % Revenue of Total | S8: =S7/(SUM($G$7,$K$7,$O$7,$S$7)) -> 0.073579089
A9: 44208 | B9: 12058.35 | C9: =B9/B8-1 -> 0.0043184616 | D9: 348.15949 | E9: =D9/D8-1 -> 0.0010965461 | H9: 311.90775 | I9: =H9/H8-1 -> -0.0088015253 | L9: 65.37344 | M9: =L9/L8-1 -> -0.024673509 | P9: 625.67887 | Q9: =P9/P8-1 -> 0.011353154
A10: 44209 | B10: 12041.1 | C10: =B10/B9-1 -> -0.001430544 | D10: 334.43139 | E10: =D10/D9-1 -> -0.039430503 | H10: 305.30677 | I10: =H10/H9-1 -> -0.021163237 | L10: 64.10878 | M10: =L10/L9-1 -> -0.019345167 | P10: 718.39153 | Q10: =P10/P9-1 -> 0.1481793
A11: 44210 | B11: 12069.5 | C11: =B11/B10-1 -> 0.002358621 | D11: 344.20312 | E11: =D11/D10-1 -> 0.029218929 | H11: 308.58417 | I11: =H11/H10-1 -> 0.010734774 | L11: 67.173161 | M11: =L11/L10-1 -> 0.047799713 | P11: 673.65941 | Q11: =P11/P10-1 -> -0.062267046
A12: 44211 | B12: 11931.2 | C12: =B12/B11-1 -> -0.011458619 | D12: 336.81474 | E12: =D12/D11-1 -> -0.021465172 | H12: 308.26104 | I12: =H12/H11-1 -> -0.0010471503 | L12: 65.713932 | M12: =L12/L11-1 -> -0.021723395 | P12: 651.40312 | Q12: =P12/P11-1 -> -0.0330379
A13: 44214 | B13: 11776.2 | C13: =B13/B12-1 -> -0.012991149 | D13: 329.66469 | E13: =D13/D12-1 -> -0.021228418 | H13: 297.41328 | I13: =H13/H12-1 -> -0.035190178 | L13: 64.449265 | M13: =L13/L12-1 -> -0.019245038 | P13: 629.32238 | Q13: =P13/P12-1 -> -0.033897189
A14: 44215 | B14: 11981.85 | C14: =B14/B13-1 -> 0.017463138 | D14: 332.04804 | E14: =D14/D13-1 -> 0.0072296127 | H14: 298.29035 | I14: =H14/H13-1 -> 0.002948999 | L14: 67.270442 | M14: =L14/L13-1 -> 0.043773614 | P14: 659.04138 | Q14: =P14/P13-1 -> 0.047223814
A15: 44216 | B15: 12078.35 | C15: =B15/B14-1 -> 0.0080538484 | D15: 336.71942 | E15: =D15/D14-1 -> 0.01406839 | H15: 295.93613 | I15: =H15/H14-1 -> -0.007892355 | L15: 66.686751 | M15: =L15/L14-1 -> -0.0086767834 | P15: 646.53044 | Q15: =P15/P14-1 -> -0.018983546
A16: 44217 | B16: 12015.95 | C16: =B16/B15-1 -> -0.0051662202 | D16: 338.10175 | E16: =D16/D15-1 -> 0.004105266 | H16: 297.64408 | I16: =H16/H15-1 -> 0.0057713307 | L16: 63.671007 | M16: =L16/L15-1 -> -0.04522254 | P16: 672.2108 | Q16: =P16/P15-1 -> 0.039720259
A17: 44218 | B17: 11854.5 | C17: =B17/B16-1 -> -0.013436324 | D17: 340.77111 | E17: =D17/D16-1 -> 0.0078951645 | H17: 289.98142 | I17: =H17/H16-1 -> -0.025744356 | L17: 62.260421 | M17: =L17/L16-1 -> -0.022154277 | P17: 667.64539 | Q17: =P17/P16-1 -> -0.0067916273
A18: 44221 | B18: 11743.7 | C18: =B18/B17-1 -> -0.0093466451 | D18: 341.10476 | E18: =D18/D17-1 -> 0.00097910194 | H18: 292.88954 | I18: =H18/H17-1 -> 0.010028621 | L18: 59.293324 | M18: =L18/L17-1 -> -0.047656235 | P18: 653.33464 | Q18: =P18/P17-1 -> -0.021434664
A19: 44223 | B19: 11546.35 | C19: =B19/B18-1 -> -0.016804805 | D19: 342.01045 | E19: =D19/D18-1 -> 0.0026551426 | H19: 293.02801 | I19: =H19/H18-1 -> 0.00047278172 | L19: 60.314783 | M19: =L19/L18-1 -> 0.017227219 | P19: 641.17485 | Q19: =P19/P18-1 -> -0.018611878
A20: 44224 | B20: 11442.55 | C20: =B20/B19-1 -> -0.0089898373 | D20: 341.15245 | E20: =D20/D19-1 -> -0.0025086829 | H20: 290.99696 | I20: =H20/H19-1 -> -0.0069312542 | L20: 60.022938 | M20: =L20/L19-1 -> -0.0048386982 | P20: 634.28288 | Q20: =P20/P19-1 -> -0.01074898
... A1435: 46309 | B1435: 22038 | C1435: =B1435/B1434-1 -> -0.0023540063 | D1435: 360.25 | E1435: =D1435/D1434-1 -> 0.0016682886 | H1435: 1400.1 | I1435: =H1435/H1434-1 -> -0.012275132 | L1435: 529.35 | M1435: =L1435/L1434-1 -> 0.0021772056 | P1435: 305.4 | Q1435: =P1435/P1434-1 -> 0.007754496
